road_collisions_us/__init__.py
road_collisions_us/download.py
road_collisions_us/utils.py
road_collisions_us/bin/__init__.py
road_collisions_us/bin/load.py
road_collisions_us/models/__init__.py
road_collisions_us/models/casualty.py
road_collisions_us/models/collision.py
road_collisions_us/models/vehicle.py
road_collisions_us-0.0.1.dist-info/METADATA
road_collisions_us-0.0.1.dist-info/WHEEL
road_collisions_us-0.0.1.dist-info/entry_points.txt
road_collisions_us-0.0.1.dist-info/top_level.txt
road_collisions_us-0.0.1.dist-info/RECORD
