Metadata-Version: 2.1
Name: road-collisions-us
Version: 0.0.1
Summary: Road collision data for the United States
Home-page: https://github.com/RobertLucey/road-collisions-us
Author: Robert Lucey
License: UNKNOWN
Platform: UNKNOWN
Requires-Python: >=3.6
Requires-Dist: road-collisions-base
Requires-Dist: boto3
